ovos_skill_youtube_music/LICENSE
ovos_skill_youtube_music/MANIFEST.in
ovos_skill_youtube_music/README.md
ovos_skill_youtube_music/__init__.py
ovos_skill_youtube_music/skill.json
ovos_skill_youtube_music/version.py
ovos_skill_youtube_music/locale/de-de/youtube.voc
ovos_skill_youtube_music/locale/en-us/youtube.voc
ovos_skill_youtube_music/locale/en-us/youtube_music_skill.voc
ovos_skill_youtube_music/locale/it-it/youtube.voc
ovos_skill_youtube_music/locale/it-it/youtube_music_skill.voc
ovos_skill_youtube_music/ovos_skill_youtube_music.egg-info/PKG-INFO
ovos_skill_youtube_music/ovos_skill_youtube_music.egg-info/SOURCES.txt
ovos_skill_youtube_music/ovos_skill_youtube_music.egg-info/dependency_links.txt
ovos_skill_youtube_music/ovos_skill_youtube_music.egg-info/entry_points.txt
ovos_skill_youtube_music/ovos_skill_youtube_music.egg-info/requires.txt
ovos_skill_youtube_music/ovos_skill_youtube_music.egg-info/top_level.txt
ovos_skill_youtube_music/res/ytmus.png
ovos_skill_youtube_music-0.1.7.dist-info/LICENSE
ovos_skill_youtube_music-0.1.7.dist-info/METADATA
ovos_skill_youtube_music-0.1.7.dist-info/WHEEL
ovos_skill_youtube_music-0.1.7.dist-info/entry_points.txt
ovos_skill_youtube_music-0.1.7.dist-info/top_level.txt
ovos_skill_youtube_music-0.1.7.dist-info/RECORD
