Metadata-Version: 2.1
Name: ovos-skill-youtube-music
Version: 0.1.7
Summary: ovos common play youtube music skill plugin
Home-page: https://github.com/OpenVoiceOS/ovos-skill-youtube-music
Author: JarbasAi
Author-email: jarbasai@mailfence.com
License: Apache-2.0
Keywords: ovos skill plugin
License-File: LICENSE
Requires-Dist: ovos-utils>=0.1.0
Requires-Dist: ovos-bus-client>=0.0.9
Requires-Dist: ovos-workshop<8.0.0,>=0.0.16
Requires-Dist: tutubo>=2.0.2
